harlow/__init__.py
harlow/optimize_neighbourhood_calculation.py
harlow/sampling/__init__.py
harlow/sampling/bayesian_optimization.py
harlow/sampling/cv_voronoi.py
harlow/sampling/fuzzy_lolavoronoi.py
harlow/sampling/lola_voronoi.py
harlow/sampling/probabilistic_sampling.py
harlow/sampling/random_sampling.py
harlow/sampling/sampling_baseclass.py
harlow/surrogating/__init__.py
harlow/surrogating/surrogate_model.py
harlow/utils/__init__.py
harlow/utils/benchmarks.py
harlow/utils/distance.py
harlow/utils/helper_functions.py
harlow/utils/log_writer.py
harlow/utils/metrics.py
harlow/utils/numba_utils.py
harlow/utils/test_functions.py
harlow/utils/transforms.py
harlow/utils/examples/__init__.py
harlow/utils/examples/model_twin_girder_betti.py
harlow/utils/examples/model_data/__init__.py
harlow/utils/examples/model_data/truck_data.py
harlow/visualization/__init__.py
harlow/visualization/corner.py
harlow/visualization/plotting.py
tests/__init__.py
tests/benchmark_tests/__init__.py
tests/benchmark_tests/benchmark_GP_surrogates.py
tests/benchmark_tests/benchmark_LV_optimization_methods.py
tests/benchmark_tests/benchmark_peaks.py
tests/benchmark_tests/benchmark_samplers.py
tests/benchmark_tests/benchmark_shekel.py
tests/integration_tests/CVVoronoi_tests.py
tests/integration_tests/FuzzyLV_tests.py
tests/integration_tests/__init__.py
tests/integration_tests/notest_surrogate.py
tests/integration_tests/test_lola_voronoi.py
tests/integration_tests/test_lola_voronoi_sampling.py
tests/integration_tests/test_test_functions.py
tests/integration_tests/utils.py
tests/unit_tests/__init__.py
tests/unit_tests/bounded_voronoi_2d.py
tests/unit_tests/test_distance.py
tests/unit_tests/test_lola_voronoi.py
tests/unit_tests/test_surrogates_multi_output.py
tests/unit_tests/test_surrogates_single_output.py
tests/unit_tests/test_transforms.py
tests/visualization/__init__.py
tests/visualization/test_corner.py
harlow-0.1.0.dist-info/LICENSE
harlow-0.1.0.dist-info/METADATA
harlow-0.1.0.dist-info/WHEEL
harlow-0.1.0.dist-info/top_level.txt
harlow-0.1.0.dist-info/RECORD
