Metadata-Version: 2.1
Name: harlow
Version: 0.1.0
Summary: Adaptive surrogate modelling
Home-page: https://github.com/TNO/harlow
Author: "Merijn de Baker"
Author-email: "merijn.debakker@tno.nl"
License: UNKNOWN
Platform: UNKNOWN
Classifier: Intended Audience :: Science/Research
Classifier: Programming Language :: Python :: 3.7
Classifier: Programming Language :: Python :: 3.8
Classifier: Programming Language :: Python :: 3.9
Classifier: Programming Language :: Python :: 3.10
Classifier: Topic :: Scientific/Engineering
Classifier: Operating System :: OS Independent
Requires-Python: >=3.7
License-File: LICENSE
Requires-Dist: numpy (<2)
Requires-Dist: numba (<1)
Requires-Dist: matplotlib (<4)
Requires-Dist: matplotlib-label-lines (<1)
Requires-Dist: corner
Requires-Dist: scikit-fuzzy
Requires-Dist: scikit-learn (<2)
Requires-Dist: scikit-optimize (<1)
Requires-Dist: tensorboardX (<3)
Requires-Dist: tensorflow (<3)
Requires-Dist: tensorflow-probability (<2)
Requires-Dist: loguru (<1)
Requires-Dist: torch (<2)
Requires-Dist: botorch (<1)
Requires-Dist: gpytorch (<2)
Requires-Dist: shortuuid
Provides-Extra: docs
Requires-Dist: six ; extra == 'docs'
Requires-Dist: sphinx (<5) ; extra == 'docs'
Requires-Dist: sphinx-copybutton (<1) ; extra == 'docs'
Requires-Dist: sphinx-inline-tabs ; extra == 'docs'
Requires-Dist: sphinxcontrib-bibtex (<3) ; extra == 'docs'
Requires-Dist: myst-parser (<1) ; extra == 'docs'
Requires-Dist: sphinx-rtd-theme (<2) ; extra == 'docs'
Requires-Dist: sphinx-rtd-dark-mode (<2) ; extra == 'docs'
Requires-Dist: furo ; extra == 'docs'
Requires-Dist: sphinx-gallery (<1) ; extra == 'docs'
Requires-Dist: sphinx-autoapi ; extra == 'docs'
Provides-Extra: lint_type_checks
Requires-Dist: pre-commit ; extra == 'lint_type_checks'
Provides-Extra: tests
Requires-Dist: pytest ; extra == 'tests'
Requires-Dist: scipy (<2) ; extra == 'tests'
Requires-Dist: coverage[toml] ; extra == 'tests'
Requires-Dist: matplotlib ; extra == 'tests'
